<?xml version="1.0" encoding="UTF-8"?>
<!--
This software is in the public domain under CC0 1.0 Universal plus a 
Grant of Patent License.

To the extent possible under law, the author(s) have dedicated all
copyright and related and neighboring rights to this software to the
public domain worldwide. This software is distributed without any
warranty.

You should have received a copy of the CC0 Public Domain Dedication
along with this software (see the LICENSE.md file). If not, see
<http://creativecommons.org/publicdomain/zero/1.0/>.
-->
<services xmlns:xsi="http://www.w3.org/2001/XMLSchema-instance" xsi:noNamespaceSchemaLocation="http://moqui.org/xsd/service-definition-1.6.xsd">

    <service verb="get" noun="PartyEmployersAndPositionClasses">
        <in-parameters><parameter name="partyId" required="true"/></in-parameters>
        <out-parameters>
            <parameter name="emplPositionClassList" type="List"/>
            <parameter name="emplPositionClassIdList" type="List"/>
            <parameter name="employerRelList" type="List"/>
        </out-parameters>
        <actions>
            <!-- Get EmplPositionClass options from EmplPositionClassParty and EmplPosition -->
            <entity-find entity-name="mantle.humanres.position.EmplPositionClassParty" list="emplPositionClassPartyList">
                <date-filter/><econdition field-name="partyId"/></entity-find>
            <if condition="emplPositionClassPartyList">
                <then><set field="emplPositionClassIdList" from="emplPositionClassPartyList.emplPositionClassId"/></then>
                <else><set field="emplPositionClassIdList" from="[]"/></else>
            </if>
            <entity-find entity-name="mantle.party.PartyToAndRelationship" list="employerRelList">
                <date-filter/><econdition field-name="fromPartyId" from="partyId"/>
                <econdition field-name="relationshipTypeEnumId" value="PrtEmployee"/>
                <order-by field-name="pseudoId,organizationName,lastName,firstName"/>
            </entity-find>
            <iterate list="employerRelList" entry="employerRel">
                <entity-find-one entity-name="mantle.humanres.employment.Employment" value-field="employment">
                    <field-map field-name="partyRelationshipId" from="employerRel.partyRelationshipId"/></entity-find-one>
                <if condition="employment">
                    <set field="emplPosition" from="employment.'mantle.humanres.position.EmplPosition'"/>
                    <if condition="emplPosition?.emplPositionClassId">
                        <script>emplPositionClassIdList.add(emplPosition?.emplPositionClassId)</script></if>
                </if>
            </iterate>
            <entity-find entity-name="mantle.humanres.position.EmplPositionClass" list="emplPositionClassList">
                <econdition field-name="emplPositionClassId" operator="in" from="emplPositionClassIdList" ignore-if-empty="true"/>
                <order-by field-name="title"/>
            </entity-find>
        </actions>
    </service>
</services>
