<?xml version="1.0" encoding="UTF-8"?>
<!--
This software is in the public domain under CC0 1.0 Universal plus a 
Grant of Patent License.

To the extent possible under law, the author(s) have dedicated all
copyright and related and neighboring rights to this software to the
public domain worldwide. This software is distributed without any
warranty.

You should have received a copy of the CC0 Public Domain Dedication
along with this software (see the LICENSE.md file). If not, see
<http://creativecommons.org/publicdomain/zero/1.0/>.
-->
<screen xmlns:xsi="http://www.w3.org/2001/XMLSchema-instance"
        xsi:noNamespaceSchemaLocation="http://moqui.org/xsd/xml-screen-1.6.xsd"
        default-menu-include="false" standalone="true">

    <parameter name="communicationEventId" required="true"/>
    <parameter name="partyId"/>

    <transition name="editMessage"><default-response url="../../EditMessage"/></transition>
    <transition name="messageThread"><default-response url=".."/></transition>

    <transition name="updateStatus"><service-call name="update#mantle.party.communication.CommunicationEvent"/>
        <default-response url=".."/></transition>
    <transition name="replyMessage">
        <service-call name="mantle.party.CommunicationServices.reply#CommunicationEvent" in-map="context"/>
        <default-response url=".."/>
    </transition>

    <actions>
        <entity-find-one entity-name="mantle.party.communication.CommunicationEvent" value-field="commEvent"/>

        <entity-find-one entity-name="mantle.party.PartyDetail" value-field="fromParty">
            <field-map field-name="partyId" from="commEvent?.fromPartyId"/></entity-find-one>
        <entity-find-one entity-name="mantle.party.PartyDetail" value-field="toParty">
            <field-map field-name="partyId" from="commEvent?.toPartyId"/></entity-find-one>
        <set field="statusId" from="commEvent.statusId"/>
    </actions>
    <widgets>
        <container-box>
            <box-header><label text="${commEvent.subject ?: 'Message'}" type="h5"/></box-header>
            <box-toolbar>
                <link url="editMessage" text="Edit"/>
                <container-dialog id="ReplyDialog" button-text="Reply">
                    <form-single name="ReplyMessageForm" transition="replyMessage">
                        <field name="communicationEventId"><default-field><hidden/></default-field></field>
                        <field name="partyId"><default-field><hidden/></default-field></field>
                        <field name="parentCommEventId" entry-name="communicationEventId"><default-field><hidden/></default-field></field>
                        <field name="subject"><default-field><text-line default-value="Re: ${commEvent.subject}" size="60"/></default-field></field>
                        <field name="body"><default-field title=""><text-area rows="10" cols="80"/></default-field></field>
                        <field name="submitButton"><default-field title="Reply"><submit/></default-field></field>
                        <field-layout>
                            <field-ref name="subject"/>
                            <field-row-big><field-ref name="body"/></field-row-big>
                            <field-ref name="submitButton"/>
                        </field-layout>
                    </form-single>
                </container-dialog>
            </box-toolbar>
            <box-body>
                <container>
                    <label text="From ${ec.resource.expand('PartyNameTemplate','',fromParty)}," type="strong"/>
                    <label text="to ${ec.resource.expand('PartyNameTemplate','',toParty)}" type="strong"/>
                    <label text="at ${ec.l10n.format(commEvent?.entryDate, 'yyyy-MM-dd HH:mm')}" type="strong"/>
                </container>
                <section-include name="StatusChangeSection" location="component://mantle-usl/template/basic/StatusWidgets.xml"/>

                <label text="${commEvent.body}" type="pre"/>
            </box-body>
        </container-box>
    </widgets>
</screen>
